twonms/config/__init__.py
twonms/config/config.py
python_twonms_config-0.1.3.dist-info/LICENSE
python_twonms_config-0.1.3.dist-info/WHEEL
python_twonms_config-0.1.3.dist-info/METADATA
python_twonms_config-0.1.3.dist-info/RECORD
